narwhal/__init__.py
narwhal/cli.py
narwhal/resources.py
narwhal/utilities.py
otto/__init__.py
otto/cli.py
otto/resources.py
otto/utilities.py
otto/validate.py
otto_bot-0.0.3.dist-info/LICENSE
otto_bot-0.0.3.dist-info/METADATA
otto_bot-0.0.3.dist-info/WHEEL
otto_bot-0.0.3.dist-info/entry_points.txt
otto_bot-0.0.3.dist-info/top_level.txt
otto_bot-0.0.3.dist-info/RECORD
