Metadata-Version: 2.1
Name: otto-bot
Version: 0.0.3
Summary: UNKNOWN
Home-page: https://github.com/mvielkind/otto-bot
Author: Matthew Vielkind
Author-email: matt@righthandcode.com
License: UNKNOWN
Platform: UNKNOWN
Classifier: Environment :: Console
Classifier: Programming Language :: Python
Classifier: Programming Language :: Python :: 3.6
Classifier: Programming Language :: Python :: 3.7
Classifier: License :: OSI Approved :: MIT License
Requires-Python: >=3.6
Requires-Dist: twilio (==6.26.1)
Requires-Dist: click (==7)
